prodb/__init__.py
prodb/_nbdev.py
prodb/card.py
prodb/core.py
prodb/examples.py
prodb-0.0.5.dist-info/LICENSE
prodb-0.0.5.dist-info/METADATA
prodb-0.0.5.dist-info/WHEEL
prodb-0.0.5.dist-info/entry_points.txt
prodb-0.0.5.dist-info/top_level.txt
prodb-0.0.5.dist-info/RECORD
