Metadata-Version: 2.1
Name: prodb
Version: 0.0.5
Summary: A pro databse using pandas csvs
Home-page: https://github.com/lukexyz/prodb/tree/master/
Author: Luke Woods
Author-email: lukedwoods@gmail.com
License: Apache Software License 2.0
Keywords: python pandas streamlit
Platform: UNKNOWN
Classifier: Development Status :: 3 - Alpha
Classifier: Intended Audience :: Developers
Classifier: Natural Language :: English
Classifier: Programming Language :: Python :: 3.6
Classifier: Programming Language :: Python :: 3.7
Classifier: Programming Language :: Python :: 3.8
Classifier: License :: OSI Approved :: Apache Software License
Requires-Python: >=3.6
Requires-Dist: pip
Requires-Dist: packaging
Provides-Extra: dev
